odoo/addons/sale_coupon_financial_risk/README.rst
odoo/addons/sale_coupon_financial_risk/__init__.py
odoo/addons/sale_coupon_financial_risk/__manifest__.py
odoo/addons/sale_coupon_financial_risk/i18n/sale_coupon_financial_risk.pot
odoo/addons/sale_coupon_financial_risk/models/__init__.py
odoo/addons/sale_coupon_financial_risk/models/sale_order.py
odoo/addons/sale_coupon_financial_risk/readme/CONTRIBUTORS.rst
odoo/addons/sale_coupon_financial_risk/readme/DESCRIPTION.rst
odoo/addons/sale_coupon_financial_risk/static/description/icon.png
odoo/addons/sale_coupon_financial_risk/static/description/index.html
odoo/addons/sale_coupon_financial_risk/tests/__init__.py
odoo/addons/sale_coupon_financial_risk/tests/test_sale_coupon_financial_risk.py
odoo13_addon_sale_coupon_financial_risk-13.0.1.1.1.dev4.dist-info/METADATA
odoo13_addon_sale_coupon_financial_risk-13.0.1.1.1.dev4.dist-info/WHEEL
odoo13_addon_sale_coupon_financial_risk-13.0.1.1.1.dev4.dist-info/top_level.txt
odoo13_addon_sale_coupon_financial_risk-13.0.1.1.1.dev4.dist-info/RECORD
